{
  "todos": [
    {
      "subject": "4",
      "completed": true,
      "id": "f534"
    },
    {
      "id": "e6d4",
      "subject": "5",
      "completed": false
    },
    {
      "id": "7304",
      "subject": "6",
      "completed": false
    },
    {
      "subject": "2321 new 12341231",
      "completed": true,
      "id": "fcce"
    },
    {
      "id": "0ab1",
      "subject": "8",
      "completed": false
    },
    {
      "id": "5c19",
      "subject": "9",
      "completed": false
    },
    {
      "id": "462b",
      "subject": "10",
      "completed": false
    },
    {
      "id": "8c27",
      "subject": "1",
      "completed": false
    },
    {
      "id": "6ff4",
      "subject": "2",
      "completed": false
    },
    {
      "id": "6c6f",
      "subject": "3",
      "completed": false
    },
    {
      "id": "b660",
      "subject": "4",
      "completed": false
    },
    {
      "id": "729b",
      "subject": "5",
      "completed": false
    },
    {
      "id": "35d0",
      "subject": "6",
      "completed": false
    },
    {
      "id": "5412",
      "subject": "1",
      "completed": false
    },
    {
      "id": "4c60",
      "subject": "123",
      "completed": false
    },
    {
      "subject": "123",
      "completed": false,
      "id": "CzYtOOj"
    },
    {
      "subject": "sell book",
      "completed": true,
      "id": "JkQdabU"
    },
    {
      "subject": "test1",
      "completed": false,
      "body": "test body",
      "id": "f03zMPL"
    },
    {
      "subject": "123",
      "completed": false,
      "body": "12345",
      "id": "-N0Ejc_"
    },
    {
      "subject": "12341",
      "completed": false,
      "body": "213124",
      "id": "AhueT41"
    },
    {
      "subject": "12323",
      "completed": false,
      "body": "123123123",
      "id": "e4TAJoK"
    },
    {
      "subject": "12321",
      "completed": false,
      "body": "32313",
      "id": "L-9ACHg"
    },
    {
      "subject": "213213",
      "completed": false,
      "body": "21321",
      "id": "HqyNyg4"
    },
    {
      "subject": "132",
      "completed": false,
      "body": "231312",
      "id": "e3kORas"
    },
    {
      "subject": "123",
      "completed": false,
      "body": "123",
      "id": "EhW1LCs"
    },
    {
      "subject": "23",
      "completed": false,
      "body": "123",
      "id": "NAb-FpX"
    },
    {
      "subject": "213",
      "completed": false,
      "body": "4123",
      "id": "dIoEwXI"
    },
    {
      "subject": "1232213123123",
      "completed": false,
      "body": "1321321",
      "id": "u9odm2j"
    },
    {
      "subject": "123",
      "completed": false,
      "body": "1231",
      "id": "fx29dO9"
    },
    {
      "subject": "123",
      "completed": false,
      "body": "3123",
      "id": "eg9Q4XY"
    },
    {
      "subject": "asd",
      "completed": false,
      "body": "asdf",
      "id": "B2k-vSp"
    },
    {
      "subject": "123",
      "completed": false,
      "body": "123",
      "id": "g6FP3a1"
    },
    {
      "subject": "12312",
      "completed": false,
      "body": "312",
      "id": "LkdSKjx"
    },
    {
      "subject": "123",
      "completed": false,
      "body": "213",
      "id": "9ClGuhn"
    },
    {
      "subject": "213",
      "completed": false,
      "body": "123",
      "id": "sCH90cQ"
    },
    {
      "subject": "213",
      "completed": false,
      "body": "123",
      "id": "Gy2Y5Ts"
    }
  ]
}